[
    {
        "id": 2097287107,
        "address": "956 S Downey Pl, Anaheim, CA 92804",
        "city": "Anaheim, CA",
        "price": 235000,
        "hoa": 386,
        "commute": 8,
        "beds": 2,
        "baths": 2,
        "type": "Townhouse",
        "link": "https://www.zillow.com/homedetails/2097287107_zpid/"
    },
    {
        "id": 2075010540,
        "address": "2626 N Tustin Ave Unit A, Santa Ana, CA 92705",
        "city": "Santa Ana, CA",
        "price": 398000,
        "hoa": 358,
        "commute": 18,
        "beds": 4,
        "baths": 3,
        "type": "Condo",
        "link": "https://www.zillow.com/homedetails/2075010540_zpid/"
    },
    {
        "id": 2117089759,
        "address": "2502 N Tustin Ave Unit C, Santa Ana, CA 92705",
        "city": "Santa Ana, CA",
        "price": 319900,
        "hoa": 290,
        "commute": 18,
        "beds": 3,
        "baths": 3,
        "type": "Townhouse",
        "link": "https://www.zillow.com/homedetails/2117089759_zpid/"
    },
    {
        "id": 17794391,
        "address": "3441 Crownsworth St, Corona, CA 92879",
        "city": "Corona, CA",
        "price": 499999,
        "hoa": 382,
        "commute": 38,
        "beds": 3,
        "baths": 2,
        "type": "Single_Family",
        "link": "https://www.zillow.com/homedetails/17794391_zpid/"
    },
    {
        "id": 17765721,
        "address": "1103 Border Ave, Corona, CA 92882",
        "city": "Corona, CA",
        "price": 474900,
        "hoa": 408,
        "commute": 38,
        "beds": 3,
        "baths": 2,
        "type": "Condo",
        "link": "https://www.zillow.com/homedetails/17765721_zpid/"
    },
    {
        "id": 79821483,
        "address": "1550 Rimpau Ave Spc 114, Corona, CA 92881",
        "city": "Corona, CA",
        "price": 279000,
        "hoa": 293,
        "commute": 38,
        "beds": 5,
        "baths": 2,
        "type": "Manufactured",
        "link": "https://www.zillow.com/homedetails/79821483_zpid/"
    },
    {
        "id": 17798411,
        "address": "2354 Fan Palm Dr, Corona, CA 92879",
        "city": "Corona, CA",
        "price": 590000,
        "hoa": 367,
        "commute": 38,
        "beds": 3,
        "baths": 3,
        "type": "Single_Family",
        "link": "https://www.zillow.com/homedetails/17798411_zpid/"
    },
    {
        "id": 17887249,
        "address": "24640 Bandit Way, Corona, CA 92883",
        "city": "Corona, CA",
        "price": 499000,
        "hoa": 396,
        "commute": 38,
        "beds": 2,
        "baths": 2,
        "type": "Manufactured",
        "link": "https://www.zillow.com/homedetails/17887249_zpid/"
    },
    {
        "id": 444561297,
        "address": "4901 Green River Rd Space 288, Corona, CA 92880",
        "city": "Corona, CA",
        "price": 299900,
        "hoa": 347,
        "commute": 38,
        "beds": 4,
        "baths": 2,
        "type": "Manufactured",
        "link": "https://www.zillow.com/homedetails/444561297_zpid/"
    },
    {
        "id": 17755118,
        "address": "777 S Temescal St Spc 102, Corona, CA 92879",
        "city": "Corona, CA",
        "price": 130000,
        "hoa": 300,
        "commute": 38,
        "beds": 3,
        "baths": 2,
        "type": "Manufactured",
        "link": "https://www.zillow.com/homedetails/17755118_zpid/"
    },
    {
        "id": 21392241,
        "address": "11410 Angell St, Norwalk, CA 90650",
        "city": "Norwalk, CA",
        "price": 599999,
        "hoa": 387,
        "commute": 28,
        "beds": 3,
        "baths": 1,
        "type": "Single_Family",
        "link": "https://www.zillow.com/homedetails/21392241_zpid/"
    },
    {
        "id": 21375514,
        "address": "11838 Gem St, Norwalk, CA 90650",
        "city": "Norwalk, CA",
        "price": 595000,
        "hoa": 385,
        "commute": 28,
        "beds": 2,
        "baths": 1,
        "type": "Single_Family",
        "link": "https://www.zillow.com/homedetails/21375514_zpid/"
    },
    {
        "id": 21108294,
        "address": "12128 161st St, Norwalk, CA 90650",
        "city": "Norwalk, CA",
        "price": 589000,
        "hoa": 361,
        "commute": 28,
        "beds": 2,
        "baths": 1,
        "type": "Single_Family",
        "link": "https://www.zillow.com/homedetails/21108294_zpid/"
    },
    {
        "id": 136702642,
        "address": "11101 Imperial Hwy Space 124, Norwalk, CA 90650",
        "city": "Norwalk, CA",
        "price": 210000,
        "hoa": 317,
        "commute": 28,
        "beds": 3,
        "baths": 2,
        "type": "Manufactured",
        "link": "https://www.zillow.com/homedetails/136702642_zpid/"
    },
    {
        "id": 21407027,
        "address": "11909 Lowemont St, Norwalk, CA 90650",
        "city": "Norwalk, CA",
        "price": 589000,
        "hoa": 343,
        "commute": 28,
        "beds": 2,
        "baths": 1,
        "type": "Single_Family",
        "link": "https://www.zillow.com/homedetails/21407027_zpid/"
    },
    {
        "id": 2064231090,
        "address": "12737 Rosecrans Ave, Norwalk, CA 90650",
        "city": "Norwalk, CA",
        "price": 250000,
        "hoa": 289,
        "commute": 28,
        "beds": 2,
        "baths": 2,
        "type": "Manufactured",
        "link": "https://www.zillow.com/homedetails/2064231090_zpid/"
    },
    {
        "id": 21396091,
        "address": "14008 Clarkdale Ave, Norwalk, CA 90650",
        "city": "Norwalk, CA",
        "price": 450000,
        "hoa": 388,
        "commute": 28,
        "beds": 2,
        "baths": 2,
        "type": "Condo",
        "link": "https://www.zillow.com/homedetails/21396091_zpid/"
    },
    {
        "id": 21391520,
        "address": "12012 1/2 Sproul St, Norwalk, CA 90650",
        "city": "Norwalk, CA",
        "price": 589900,
        "hoa": 395,
        "commute": 28,
        "beds": 3,
        "baths": 3,
        "type": "Condo",
        "link": "https://www.zillow.com/homedetails/21391520_zpid/"
    },
    {
        "id": 136696989,
        "address": "16341 Pioneer Blvd Space 11, Norwalk, CA 90650",
        "city": "Norwalk, CA",
        "price": 110000,
        "hoa": 366,
        "commute": 28,
        "beds": 2,
        "baths": 1,
        "type": "Manufactured",
        "link": "https://www.zillow.com/homedetails/136696989_zpid/"
    }
]